<?xml version="1.0" encoding="utf-8"?>
<search>
  
  
  
  <entry>
    <title>mac锁屏后如何让程序继续运行</title>
    <link href="/2023/10/27/others/mac%E9%94%81%E5%B1%8F%E5%90%8E%E8%AE%A9%E7%A8%8B%E5%BA%8F%E7%BB%A7%E7%BB%AD%E8%BF%90%E8%A1%8C/"/>
    <url>/2023/10/27/others/mac%E9%94%81%E5%B1%8F%E5%90%8E%E8%AE%A9%E7%A8%8B%E5%BA%8F%E7%BB%A7%E7%BB%AD%E8%BF%90%E8%A1%8C/</url>
    
    <content type="html"><![CDATA[<h2 id="mac锁屏后让程序继续运行"><a href="#mac锁屏后让程序继续运行" class="headerlink" title="mac锁屏后让程序继续运行"></a>mac锁屏后让程序继续运行</h2><p>在日常工作中，我们经常需要使用计算机进行各种操作。但是，有时候我们需要离开电脑，或者需要让电脑保持活跃状态，以便程序继续运行。在这种情况下，我们可以使用一些技巧来让mac锁屏后让程序继续运行。</p><h2 id="使用caffeine"><a href="#使用caffeine" class="headerlink" title="使用caffeine"></a>使用caffeine</h2><p>caffeine是一款mac上的小工具，可以让电脑保持活跃状态，防止锁屏和休眠。使用caffeine非常简单，只需要在应用程序中找到caffeine，然后点击它的图标即可。此时，电脑就会保持活跃状态，不会锁屏或休眠。当你需要让电脑恢复正常状态时，只需要再次点击caffeine的图标即可。</p><h2 id="使用命令行"><a href="#使用命令行" class="headerlink" title="使用命令行"></a>使用命令行</h2><p>除了使用caffeine，我们还可以通过命令行来让mac保持活跃状态。具体操作步骤如下：</p><ol><li><p>打开终端应用程序。</p></li><li><p>输入以下命令：</p><figure class="highlight shell"><table><tr><td class="gutter"><pre><span class="line">1</span><br></pre></td><td class="code"><pre><code class="hljs shell">caffeinate -s<br></code></pre></td></tr></table></figure></li><li><p>按下回车键，电脑就会开始保持活跃状态，不会锁屏或休眠。</p></li><li><p>当你需要让电脑恢复正常状态时，只需要按下ctrl+c键即可。</p></li></ol><h2 id="使用自带的屏幕保护程序"><a href="#使用自带的屏幕保护程序" class="headerlink" title="使用自带的屏幕保护程序"></a>使用自带的屏幕保护程序</h2><p>除了上述方法，还可以使用mac自带的屏幕保护程序来让电脑保持活跃状态。具体操作步骤如下：</p><ol><li><p>打开系统偏好设置，进入“桌面与屏幕保护”选项。</p></li><li><p>在屏幕保护选项卡中选择“漫游屏幕保护”。</p></li><li><p>点击“屏幕保护选项”，在弹出的窗口中选择“防止计算机进入睡眠模式”。</p></li><li><p>点击“确定”按钮，然后关闭偏好设置窗口。</p></li></ol><p>此时，电脑就会保持活跃状态，不会锁屏或休眠。当你需要让电脑恢复正常状态时，只需要关闭屏幕保护程序即可。</p>]]></content>
    
    
    <categories>
      
      <category>其他</category>
      
    </categories>
    
    
  </entry>
  
  
  
  <entry>
    <title>Hello World</title>
    <link href="/2023/10/26/hello-world/"/>
    <url>/2023/10/26/hello-world/</url>
    
    <content type="html"><![CDATA[<p>Welcome to <a href="https://hexo.io/">Hexo</a>! This is your very first post. Check <a href="https://hexo.io/docs/">documentation</a> for more info. If you get any problems when using Hexo, you can find the answer in <a href="https://hexo.io/docs/troubleshooting.html">troubleshooting</a> or you can ask me on <a href="https://github.com/hexojs/hexo/issues">GitHub</a>.</p><h2 id="Quick-Start"><a href="#Quick-Start" class="headerlink" title="Quick Start"></a>Quick Start</h2><h3 id="Create-a-new-post"><a href="#Create-a-new-post" class="headerlink" title="Create a new post"></a>Create a new post</h3><figure class="highlight bash"><table><tr><td class="gutter"><pre><span class="line">1</span><br></pre></td><td class="code"><pre><code class="hljs bash">$ hexo new <span class="hljs-string">&quot;My New Post&quot;</span><br></code></pre></td></tr></table></figure><p>More info: <a href="https://hexo.io/docs/writing.html">Writing</a></p><h3 id="Run-server"><a href="#Run-server" class="headerlink" title="Run server"></a>Run server</h3><figure class="highlight bash"><table><tr><td class="gutter"><pre><span class="line">1</span><br></pre></td><td class="code"><pre><code class="hljs bash">$ hexo server<br></code></pre></td></tr></table></figure><p>More info: <a href="https://hexo.io/docs/server.html">Server</a></p><h3 id="Generate-static-files"><a href="#Generate-static-files" class="headerlink" title="Generate static files"></a>Generate static files</h3><figure class="highlight bash"><table><tr><td class="gutter"><pre><span class="line">1</span><br></pre></td><td class="code"><pre><code class="hljs bash">$ hexo generate<br></code></pre></td></tr></table></figure><p>More info: <a href="https://hexo.io/docs/generating.html">Generating</a></p><h3 id="Deploy-to-remote-sites"><a href="#Deploy-to-remote-sites" class="headerlink" title="Deploy to remote sites"></a>Deploy to remote sites</h3><figure class="highlight bash"><table><tr><td class="gutter"><pre><span class="line">1</span><br></pre></td><td class="code"><pre><code class="hljs bash">$ hexo deploy<br></code></pre></td></tr></table></figure><p>More info: <a href="https://hexo.io/docs/one-command-deployment.html">Deployment</a></p>]]></content>
    
    
    
  </entry>
  
  
  
  <entry>
    <title>经济相关概念和知识--(1)</title>
    <link href="/2023/05/10/%E7%BB%8F%E6%B5%8E%E5%AD%A6%E7%9B%B8%E5%85%B3%E6%A6%82%E5%BF%B5/"/>
    <url>/2023/05/10/%E7%BB%8F%E6%B5%8E%E5%AD%A6%E7%9B%B8%E5%85%B3%E6%A6%82%E5%BF%B5/</url>
    
    <content type="html"><![CDATA[<h1 id="一些你必须懂的专业词汇"><a href="#一些你必须懂的专业词汇" class="headerlink" title="一些你必须懂的专业词汇"></a>一些你必须懂的专业词汇</h1><h2 id="M0-M1-M2货币供应量"><a href="#M0-M1-M2货币供应量" class="headerlink" title="M0\M1\M2货币供应量"></a>M0\M1\M2货币供应量</h2><p>三个定义M代表monetary。</p><ul><li>M0表示流通中的现金，即居民手中的资金，一般来说M0越大表示老百姓手中的钱越宽裕。</li><li>狭义货币量M1&#x3D;M0+企业活期存款，流动性仅次于M0，代表大家目前的购买能力。</li><li>广义货币量M2&#x3D;M1+定期存款+储蓄存款+其他存款+证券公司客户保证金。M2不仅反映现实的购买力，还反映潜在的购买力。</li><li>关于这些数据可以查询<a href="https://mp.weixin.qq.com/s/LBIMYzOKAt4NQ7WlqekKZg">相关公众号</a></li></ul><p>GDP&#x2F;CPI&#x2F;PPI&#x2F;PMI相关指标<br>这些指标可以在<a href="https://data.stats.gov.cn/index.htm">国家统计局官网</a>查询</p><p><a href="https://zh.tradingeconomics.com/">全世界的相关指标</a></p><p>GDP国民生产总值：<br>GDP（国内生产总值）是衡量一个国家或地区经济总量的指标，表示在一定时间内，一个国家或地区所有企业、个人和政府所生产的全部商品和服务的价值总和。GDP是衡量一个国家或地区经济发展水平的重要指标，也是制定宏观经济政策的重要参考依据。<br>CPI居民消费指数</p><ol><li>CPI（consumer price index 居民消费价格指数）是衡量一定时期内一篮子消费品和服务价格变动情况的指标，反映了居民购买日常消费品和服务的成本变化。CPI是衡量通货膨胀水平的重要指标，也是制定货币政策的重要参考依据。<br>PPI</li><li>PPI（product price index 生产者出厂价格指数）是衡量一定时期内工业生产部门生产的商品出厂价格变动情况的指标，反映了工业生产部门生产成本和利润水平的变化。PPI是衡量物价上涨对生产企业的影响的重要指标，也是制定宏观经济政策的重要参考依据。<br>PMI</li><li>PMI（采购经理人指数）是衡量制造业和非制造业采购经理人对生产活动的信心和预期的指标，反映了制造业和非制造业企业生产活动的扩张或收缩情况。PMI是衡量经济景气度的重要指标，也是制定宏观经济政策的重要参考依据。<br><a href="https://fred.stlouisfed.org/series/FEDFUNDS">美联储利率</a></li></ol><h2 id="关于供给通缩和需求通缩"><a href="#关于供给通缩和需求通缩" class="headerlink" title="关于供给通缩和需求通缩"></a>关于供给通缩和需求通缩</h2><ol><li>供给通缩：本质是生产成本上升或者供应减少，导致商品或者服务供应减少。指标包含生产率下降、原材料价格上升、劳动力短缺等。可观察PPI指数。</li><li>需求通缩：本质是消费者支出减少或信心下降。指标包含收入增长缓慢、消费信心下降、失业率上升等。可以参考CPI指数。</li></ol><h2 id="利率、通胀率、生产总值增长率参考值"><a href="#利率、通胀率、生产总值增长率参考值" class="headerlink" title="利率、通胀率、生产总值增长率参考值"></a>利率、通胀率、生产总值增长率参考值</h2><ol><li>利率：2%～4%为合理范围（指的是中国的央行基准利率）</li><li>通胀率：2%～3% 为合理范围</li><li>国民生产总值： 2%～3% 为合理范围</li></ol>]]></content>
    
    
    <categories>
      
      <category>经济</category>
      
    </categories>
    
    
    <tags>
      
      <tag>金融</tag>
      
    </tags>
    
  </entry>
  
  
  
  
</search>
